shadowprover/__init__.py
shadowprover/cli.py
shadowprover/sandbox.py
shadowprover/setup.py
shadowprover/shadowprover.py
shadowprover/experimental/__init__.py
shadowprover/experimental/sst_prover.py
shadowprover/fol/__init__.py
shadowprover/fol/eprover.py
shadowprover/fol/fol_prover.py
shadowprover/fol/proof.py
shadowprover/fol/tptp.py
shadowprover/inference_systems/__init__.py
shadowprover/inference_systems/base_inference_system.py
shadowprover/inference_systems/base_schema.py
shadowprover/inference_systems/cognitive_calculus.py
shadowprover/inference_systems/reader.py
shadowprover/inference_systems/unifcation_inference_system.py
shadowprover/inference_systems/unification_schema.py
shadowprover/pyarmor_runtime_000000/__init__.py
shadowprover/pyarmor_runtime_000000/darwin_x86_64/pyarmor_runtime.so
shadowprover/pyarmor_runtime_000000/linux_x86_64/pyarmor_runtime.so
shadowprover/pyarmor_runtime_000000/windows_x86_64/pyarmor_runtime.pyd
shadowprover/reasoners/__init__.py
shadowprover/reasoners/instantiate_universals.py
shadowprover/reasoners/planner.py
shadowprover/reasoners/planner_meta.py
shadowprover/reasoners/shadow_prover.py
shadowprover/reasoners/shadow_proverold.py
shadowprover/reasoners/shadow_repr.py
shadowprover/reasoners/utils.py
shadowprover/syntax/__init__.py
shadowprover/syntax/common.py
shadowprover/syntax/expression.py
shadowprover/syntax/modal.py
shadowprover/syntax/reader.py
shadowprover/unifiers/__init__.py
shadowprover/unifiers/first_order_unify.py
shadowprover-1.2.56.dist-info/METADATA
shadowprover-1.2.56.dist-info/WHEEL
shadowprover-1.2.56.dist-info/entry_points.txt
shadowprover-1.2.56.dist-info/top_level.txt
shadowprover-1.2.56.dist-info/RECORD
