Metadata-Version: 2.4
Name: shadowprover
Version: 1.2.56
Home-page: https://github.com/naveensundarg/py_laser
Author: Naveen Sundar Govindarajulu
Author-email: naveensundarg@gmail.com
Keywords: shadowprover
Classifier: Development Status :: 2 - Pre-Alpha
Classifier: Intended Audience :: Developers
Classifier: Natural Language :: English
Classifier: Programming Language :: Python :: 3.8
Requires-Python: >=3.8
Requires-Dist: Click>=7.0
Requires-Dist: edn_format
Requires-Dist: pydantic
Requires-Dist: pyparsing
Requires-Dist: fuzzywuzzy
Requires-Dist: loguru
Requires-Dist: colorama
Dynamic: author
Dynamic: author-email
Dynamic: classifier
Dynamic: description
Dynamic: description-content-type
Dynamic: home-page
Dynamic: keywords
Dynamic: requires-dist
Dynamic: requires-python
